<?xml version="1.0" encoding="UTF-8"?>
<MetaDataObject xmlns="http://v8.1c.ru/8.3/MDClasses" xmlns:app="http://v8.1c.ru/8.2/managed-application/core" xmlns:cfg="http://v8.1c.ru/8.1/data/enterprise/current-config" xmlns:cmi="http://v8.1c.ru/8.2/managed-application/cmi" xmlns:ent="http://v8.1c.ru/8.1/data/enterprise" xmlns:lf="http://v8.1c.ru/8.2/managed-application/logform" xmlns:style="http://v8.1c.ru/8.1/data/ui/style" xmlns:sys="http://v8.1c.ru/8.1/data/ui/fonts/system" xmlns:v8="http://v8.1c.ru/8.1/data/core" xmlns:v8ui="http://v8.1c.ru/8.1/data/ui" xmlns:web="http://v8.1c.ru/8.1/data/ui/colors/web" xmlns:win="http://v8.1c.ru/8.1/data/ui/colors/windows" xmlns:xen="http://v8.1c.ru/8.3/xcf/enums" xmlns:xpr="http://v8.1c.ru/8.3/xcf/predef" xmlns:xr="http://v8.1c.ru/8.3/xcf/readable" xmlns:xs="http://www.w3.org/2001/XMLSchema" xmlns:xsi="http://www.w3.org/2001/XMLSchema-instance" version="2.20">
	<Constant uuid="20923cbd-0e72-4907-83d6-d885302b48d6">
		<InternalInfo>
			<xr:GeneratedType name="ConstantManager.ИспользоватьАктыРасхожденийПослеПриемкиПоПриемкамТоваровДавальца2_5" category="Manager">
				<xr:TypeId>3ff73136-780a-466a-83d7-52a24cc97975</xr:TypeId>
				<xr:ValueId>b0a30f2a-83b2-4872-98e1-08e70f1bb50d</xr:ValueId>
			</xr:GeneratedType>
			<xr:GeneratedType name="ConstantValueManager.ИспользоватьАктыРасхожденийПослеПриемкиПоПриемкамТоваровДавальца2_5" category="ValueManager">
				<xr:TypeId>b3a57a13-b622-44dd-97d8-2a3e5900bff5</xr:TypeId>
				<xr:ValueId>07b72b0b-e86a-4e36-b325-ddb24e61e6a6</xr:ValueId>
			</xr:GeneratedType>
			<xr:GeneratedType name="ConstantValueKey.ИспользоватьАктыРасхожденийПослеПриемкиПоПриемкамТоваровДавальца2_5" category="ValueKey">
				<xr:TypeId>46babd27-4f82-4421-a248-b2514e0705aa</xr:TypeId>
				<xr:ValueId>afc447ef-709a-4e6c-9b69-16767d51d81c</xr:ValueId>
			</xr:GeneratedType>
		</InternalInfo>
		<Properties>
			<Name>ИспользоватьАктыРасхожденийПослеПриемкиПоПриемкамТоваровДавальца2_5</Name>
			<Synonym>
				<v8:item>
					<v8:lang>ru</v8:lang>
					<v8:content>Использовать акты расхождений после приемки по приемкам товаров давальца</v8:content>
				</v8:item>
				<v8:item>
					<v8:lang>en</v8:lang>
					<v8:content>Use discrepancy reports following receipt by goods receipt from the provider</v8:content>
				</v8:item>
			</Synonym>
			<Comment/>
			<Type>
				<v8:Type>xs:boolean</v8:Type>
			</Type>
			<UseStandardCommands>false</UseStandardCommands>
			<DefaultForm/>
			<ExtendedPresentation/>
			<Explanation/>
			<PasswordMode>false</PasswordMode>
			<Format/>
			<EditFormat/>
			<ToolTip>
				<v8:item>
					<v8:lang>ru</v8:lang>
					<v8:content>Управление использованием актов о расхождении после приемки товаров на хранение</v8:content>
				</v8:item>
				<v8:item>
					<v8:lang>en</v8:lang>
					<v8:content>Management of discrepancy reports following goods receipt for storage</v8:content>
				</v8:item>
			</ToolTip>
			<MarkNegatives>false</MarkNegatives>
			<Mask/>
			<MultiLine>false</MultiLine>
			<ExtendedEdit>false</ExtendedEdit>
			<MinValue xsi:nil="true"/>
			<MaxValue xsi:nil="true"/>
			<FillChecking>DontCheck</FillChecking>
			<ChoiceFoldersAndItems>Items</ChoiceFoldersAndItems>
			<ChoiceParameterLinks/>
			<ChoiceParameters/>
			<QuickChoice>Auto</QuickChoice>
			<ChoiceForm/>
			<LinkByType/>
			<ChoiceHistoryOnInput>Auto</ChoiceHistoryOnInput>
			<DataLockControlMode>Automatic</DataLockControlMode>
			<DataHistory>DontUse</DataHistory>
			<UpdateDataHistoryImmediatelyAfterWrite>false</UpdateDataHistoryImmediatelyAfterWrite>
			<ExecuteAfterWriteDataHistoryVersionProcessing>false</ExecuteAfterWriteDataHistoryVersionProcessing>
		</Properties>
	</Constant>
</MetaDataObject>